[
    {
        "Name": "Daisy",
        "Height": 61.08,
        "Weight": 76.1
    },
    {
        "Name": "Deborah",
        "Height": 60.44,
        "Weight": 80.68
    },
    {
        "Name": "Isabel",
        "Height": 61.88,
        "Weight": 72.89
    },
    {
        "Name": "Stella",
        "Height": 65.74,
        "Weight": 79.88
    },
    {
        "Name": "Debra",
        "Height": 63.72,
        "Weight": 100.82
    },
    {
        "Name": "Beverly",
        "Height": 57.57,
        "Weight": 67.25
    },
    {
        "Name": "Vera",
        "Height": 57.26,
        "Weight": 61.22
    },
    {
        "Name": "Angela",
        "Height": 57.11,
        "Weight": 117.62
    },
    {
        "Name": "Lucy",
        "Height": 62.5,
        "Weight": 115.24
    },
    {
        "Name": "Lauren",
        "Height": 70.79,
        "Weight": 112.55
    },
    {
        "Name": "Janet",
        "Height": 59.83,
        "Weight": 102.72
    },
    {
        "Name": "Loretta",
        "Height": 69.12,
        "Weight": 74.05
    },
    {
        "Name": "Tracey",
        "Height": 58.56,
        "Weight": 64.0
    },
    {
        "Name": "Beatrice",
        "Height": 57.5,
        "Weight": 62.65
    }
]